siliconcompiler/__init__.py
siliconcompiler/_common.py
siliconcompiler/_metadata.py
siliconcompiler/asic.py
siliconcompiler/checklist.py
siliconcompiler/design.py
siliconcompiler/flowgraph.py
siliconcompiler/fpga.py
siliconcompiler/library.py
siliconcompiler/pdk.py
siliconcompiler/project.py
siliconcompiler/schematic.py
siliconcompiler/tool.py
siliconcompiler/apps/__init__.py
siliconcompiler/apps/_common.py
siliconcompiler/apps/sc_dashboard.py
siliconcompiler/apps/sc_install.py
siliconcompiler/apps/sc_issue.py
siliconcompiler/apps/sc_remote.py
siliconcompiler/apps/sc_server.py
siliconcompiler/apps/sc_show.py
siliconcompiler/apps/smake.py
siliconcompiler/apps/utils/replay.py
siliconcompiler/apps/utils/summarize.py
siliconcompiler/checklists/__init__.py
siliconcompiler/checklists/oh_tapeout.py
siliconcompiler/constraints/__init__.py
siliconcompiler/constraints/asic_component.py
siliconcompiler/constraints/asic_floorplan.py
siliconcompiler/constraints/asic_pins.py
siliconcompiler/constraints/asic_timing.py
siliconcompiler/constraints/fpga_timing.py
siliconcompiler/constraints/timing_mode.py
siliconcompiler/data/__init__.py
siliconcompiler/data/heartbeat.sdc
siliconcompiler/data/heartbeat.v
siliconcompiler/data/logo.png
siliconcompiler/data/RobotoMono/LICENSE.txt
siliconcompiler/data/RobotoMono/RobotoMono-Regular.ttf
siliconcompiler/data/RobotoMono/__init__.py
siliconcompiler/data/demo_fpga/heartbeat.pcf
siliconcompiler/data/demo_fpga/heartbeat.sdc
siliconcompiler/data/demo_fpga/tech_flops.lib
siliconcompiler/data/demo_fpga/tech_flops.v
siliconcompiler/data/demo_fpga/vtr_primitives.lib
siliconcompiler/data/demo_fpga/z1000.xml
siliconcompiler/data/demo_fpga/z1000_constraint_map.json
siliconcompiler/data/demo_fpga/z1000_rr_graph.xml
siliconcompiler/data/demo_fpga/z1000_yosys_config.json
siliconcompiler/data/templates/__init__.py
siliconcompiler/data/templates/email/__init__.py
siliconcompiler/data/templates/email/general.j2
siliconcompiler/data/templates/email/summary.j2
siliconcompiler-0.36.4.dist-info/licenses/LICENSE
siliconcompiler-0.36.4.dist-info/METADATA
siliconcompiler-0.36.4.dist-info/WHEEL
siliconcompiler-0.36.4.dist-info/entry_points.txt
siliconcompiler-0.36.4.dist-info/top_level.txt
siliconcompiler-0.36.4.dist-info/RECORD
