Metadata-Version: 2.4
Name: siliconcompiler
Version: 0.36.4
Summary: A compiler framework that automates translation from source code to silicon.
Author: Zero ASIC
License: Apache License 2.0
Project-URL: Homepage, https://www.siliconcompiler.com
Project-URL: Documentation, https://docs.siliconcompiler.com
Project-URL: Repository, https://github.com/siliconcompiler/siliconcompiler
Project-URL: Issues, https://github.com/siliconcompiler/siliconcompiler/issues
Project-URL: Discussion, https://github.com/siliconcompiler/siliconcompiler/discussions
Classifier: Environment :: Console
Classifier: License :: OSI Approved :: Apache Software License
Classifier: Programming Language :: Python :: 3.9
Classifier: Programming Language :: Python :: 3.10
Classifier: Programming Language :: Python :: 3.11
Classifier: Programming Language :: Python :: 3.12
Classifier: Programming Language :: Python :: 3.13
Classifier: Programming Language :: Python :: 3.14
Classifier: Operating System :: POSIX :: Linux
Classifier: Operating System :: MacOS
Classifier: Operating System :: Microsoft :: Windows
Classifier: Topic :: Scientific/Engineering :: Electronic Design Automation (EDA)
Classifier: Topic :: Software Development :: Build Tools
Requires-Python: >=3.9
License-File: LICENSE
Requires-Dist: aiohttp<3.14.0,>=3.10.11
Requires-Dist: distro<2.0.0,>=1.9.0
Requires-Dist: docker<8.0.0,>=7.1.0
Requires-Dist: fastjsonschema<2.22.0,>=2.20.0
Requires-Dist: graphviz<0.22,>=0.20
Requires-Dist: orjson<4,>=3.11.0
Requires-Dist: packaging<26,>=21.3
Requires-Dist: requests<2.33.0,>=2.32.0
Requires-Dist: Pillow<11.4.0,>=11.3.0
Requires-Dist: PyYAML<7.0.0,>=6.0.0
Requires-Dist: GitPython<3.2,>=3.1.44
Requires-Dist: PyGithub<2.9.0,>=2.8.0
Requires-Dist: urllib3>=1.26.0
Requires-Dist: lambdapdk>=0.2.7
Requires-Dist: fasteners>=0.20
Requires-Dist: pandas>=1.1.5
Requires-Dist: psutil>=5.8.0
Requires-Dist: Jinja2>=2.11.3
Requires-Dist: pyslang==10.0.0
Requires-Dist: importlib_metadata; python_version < "3.10"
Requires-Dist: streamlit==1.46.1; python_full_version != "3.9.7"
Requires-Dist: streamlit_agraph==0.0.45; python_full_version != "3.9.7"
Requires-Dist: streamlit-antd-components==0.3.2; python_full_version != "3.9.7"
Requires-Dist: streamlit_javascript==0.1.5; python_full_version != "3.9.7"
Requires-Dist: streamlit-autorefresh==1.0.1; python_full_version != "3.9.7"
Requires-Dist: rich<15.0.0,>=14.0.0
Provides-Extra: test
Requires-Dist: pytest==8.4.2; extra == "test"
Requires-Dist: pytest-xdist==3.8.0; extra == "test"
Requires-Dist: pytest-timeout==2.4.0; extra == "test"
Requires-Dist: pytest-asyncio==1.2.0; extra == "test"
Requires-Dist: pytest-cov==7.0.0; extra == "test"
Requires-Dist: responses==0.25.8; extra == "test"
Requires-Dist: PyVirtualDisplay==3.0; extra == "test"
Provides-Extra: lint
Requires-Dist: flake8==7.3.0; extra == "lint"
Requires-Dist: tclint==0.7.0; extra == "lint"
Requires-Dist: codespell==2.4.1; extra == "lint"
Provides-Extra: docs
Requires-Dist: Sphinx<8.3,>=7.4; extra == "docs"
Requires-Dist: pip-licenses==5.5.0; extra == "docs"
Requires-Dist: pydata-sphinx-theme==0.16.1; extra == "docs"
Requires-Dist: sc-leflib>=0.2.0; extra == "docs"
Provides-Extra: optimizer
Requires-Dist: google-vizier[jax]==0.1.21; python_version >= "3.10" and extra == "optimizer"
Provides-Extra: cocotb
Requires-Dist: cocotb<2.1.0,>=2.0.1; (python_version >= "3.7" and python_version <= "3.13") and extra == "cocotb"
Dynamic: license-file
